<?xml version="1.0" encoding="utf-8"?>
<!DOCTYPE hibernate-mapping PUBLIC "-//Hibernate/Hibernate Mapping DTD 3.0//EN"
"http://hibernate.sourceforge.net/hibernate-mapping-3.0.dtd">
<!-- 
    Mapping file autogenerated by MyEclipse Persistence Tools
-->
<hibernate-mapping>
    <class name="entity.WebMachin" table="WEB_MACHIN" schema="KAYUEN">
        <composite-id name="id" class="entity.WebMachinId">
            <key-property name="factNo" type="java.lang.String">
                <column name="FACT_NO" length="5" />
            </key-property>
            <key-property name="billNo" type="java.lang.String">
                <column name="BILL_NO" length="12" />
            </key-property>
            <key-property name="yymm" type="java.util.Date">
                <column name="YYMM" length="7" />
            </key-property>
        </composite-id>
        <property name="factCode" type="java.lang.String">
            <column name="FACT_CODE" length="10" />
        </property>
        <property name="machineNum" type="java.lang.Double">
            <column name="MACHINE_NUM" precision="5" scale="1" />
        </property>
        <property name="workDay" type="java.lang.Double">
            <column name="WORK_DAY" precision="4" scale="1" />
        </property>
        <property name="realDemo" type="java.lang.Double">
            <column name="REAL_DEMO" precision="5" scale="1" />
        </property>
        <property name="dayDemo" type="java.lang.Double">
            <column name="DAY_DEMO" precision="5" scale="1" />
        </property>
        <property name="weitEvg" type="java.lang.Double">
            <column name="WEIT_EVG" precision="6" scale="3" />
        </property>
        <property name="turnNo" type="java.lang.Double">
            <column name="TURN_NO" precision="5" scale="1" />
        </property>
        <property name="turnAct" type="java.lang.Double">
            <column name="TURN_ACT" precision="5" scale="1" />
        </property>
        <property name="dateB" type="java.lang.String">
            <column name="DATE_B" length="8" />
        </property>
        <property name="dateE" type="java.lang.String">
            <column name="DATE_E" length="8" />
        </property>
        <property name="lockMk" type="java.lang.String">
            <column name="LOCK_MK" length="1" />
        </property>
        <property name="userNo" type="java.lang.String">
            <column name="USER_NO" length="10" />
        </property>
        <property name="dateTime" type="java.lang.String">
            <column name="DATE_TIME" length="20" />
        </property>
    </class>
</hibernate-mapping>
