<?xml version="1.0" encoding="utf-8"?>
<!DOCTYPE hibernate-mapping PUBLIC "-//Hibernate/Hibernate Mapping DTD 3.0//EN"
"http://hibernate.sourceforge.net/hibernate-mapping-3.0.dtd">
<!-- 
    Mapping file autogenerated by MyEclipse Persistence Tools
-->
<hibernate-mapping>
    <class name="entity.Webproduted" table="WEBPRODUTED" schema="WEB">
        <composite-id name="id" class="entity.WebprodutedId">
            <key-property name="factNo" type="java.lang.String">
                <column name="FACT_NO" length="10" />
            </key-property>
            <key-property name="factCode" type="java.lang.String">
                <column name="FACT_CODE" length="20" />
            </key-property>
            <key-property name="yymm" type="java.sql.Timestamp">
                <column name="YYMM" length="7" />
            </key-property>
        </composite-id>
        <property name="storenum" type="java.lang.Double">
            <column name="STORENUM" precision="12" scale="3" />
        </property>
        <property name="noliststorenum" type="java.lang.Double">
            <column name="NOLISTSTORENUM" precision="12" scale="3" />
        </property>
        <property name="makestorenum" type="java.lang.Double">
            <column name="MAKESTORENUM" precision="12" scale="3" />
        </property>
        <property name="outnum" type="java.lang.Double">
            <column name="OUTNUM" precision="12" scale="3" />
        </property>
        <property name="innum" type="java.lang.Double">
            <column name="INNUM" precision="12" scale="3" />
        </property>
        <property name="instorenum" type="java.lang.Double">
            <column name="INSTORENUM" precision="12" scale="3" />
        </property>
        <property name="minusnum" type="java.lang.Double">
            <column name="MINUSNUM" precision="12" scale="3" />
        </property>
        <property name="username" type="java.lang.String">
            <column name="USERNAME" length="20" />
        </property>
        <property name="usernameUd" type="java.lang.String">
            <column name="USERNAME_UD" length="50"  />
        </property>
    </class>
</hibernate-mapping>
